g2p_zh_en
tests
