Metadata-Version: 2.1
Name: g2p-zh-en
Version: 0.1.1
Summary: g2p-zh-en
Home-page: https://github.com/skysbird/g2p-zh-en
Author: gp-zh-en
Author-email: skysbird@gmail.com
License: GNU General Public License v3
Keywords: g2p_zh_en
Platform: UNKNOWN
Classifier: Development Status :: 2 - Pre-Alpha
Classifier: Intended Audience :: Developers
Classifier: License :: OSI Approved :: GNU General Public License v3 (GPLv3)
Classifier: Natural Language :: English
Classifier: Programming Language :: Python :: 3
Classifier: Programming Language :: Python :: 3.6
Classifier: Programming Language :: Python :: 3.7
Classifier: Programming Language :: Python :: 3.8
Requires-Python: >=3.6
License-File: LICENSE
License-File: AUTHORS.rst
